click_odoo_contrib/__init__.py
click_odoo_contrib/_addon_hash.py
click_odoo_contrib/_backup.py
click_odoo_contrib/_dbutils.py
click_odoo_contrib/backupdb.py
click_odoo_contrib/copydb.py
click_odoo_contrib/dropdb.py
click_odoo_contrib/gitutils.py
click_odoo_contrib/initdb.py
click_odoo_contrib/listdb.py
click_odoo_contrib/makepot.py
click_odoo_contrib/manifest.py
click_odoo_contrib/restoredb.py
click_odoo_contrib/uninstall.py
click_odoo_contrib/update.py
click_odoo_contrib-1.23.1.dist-info/licenses/LICENSE
tests/__init__.py
tests/compat.py
tests/conftest.py
tests/test_addon_hash.py
tests/test_backupdb.py
tests/test_copydb.py
tests/test_dropdb.py
tests/test_gitutils.py
tests/test_initdb.py
tests/test_listdb.py
tests/test_makepot.py
tests/test_manifest.py
tests/test_restoredb.py
tests/test_uninstall.py
tests/test_update.py
tests/test_update_only_compute_hashes.py
tests/data/test_addon_hash/README.rst
tests/data/test_addon_hash/data/f1.xml
tests/data/test_addon_hash/data/f2.xml
tests/data/test_addon_hash/i18n/en.po
tests/data/test_addon_hash/i18n/en_US.po
tests/data/test_addon_hash/i18n/fr.po
tests/data/test_addon_hash/i18n/fr_BE.po
tests/data/test_addon_hash/i18n/test.pot
tests/data/test_addon_hash/i18n_extra/en.po
tests/data/test_addon_hash/i18n_extra/fr.po
tests/data/test_addon_hash/i18n_extra/nl_NL.po
tests/data/test_addon_hash/models/stuff.py
tests/data/test_addon_hash/models/stuff.pyc
tests/data/test_addon_hash/models/stuff.pyo
tests/data/test_addon_hash/static/src/some.js
tests/data/test_initdb/addon1/__init__.py
tests/data/test_initdb/addon1/__manifest__.py
tests/data/test_makepot/addon_test_makepot/__init__.py
tests/data/test_makepot/addon_test_makepot/__manifest__.py
tests/data/test_makepot/addon_test_makepot/i18n/fr.po.bad
tests/data/test_makepot/addon_test_makepot/i18n/fr.po.fuzzy
tests/data/test_makepot/addon_test_makepot/i18n/fr.po.old
tests/data/test_makepot/addon_test_makepot/models/__init__.py
tests/data/test_makepot/addon_test_makepot/models/testmodel.py
click_odoo_contrib-1.23.1.dist-info/METADATA
click_odoo_contrib-1.23.1.dist-info/WHEEL
click_odoo_contrib-1.23.1.dist-info/entry_points.txt
click_odoo_contrib-1.23.1.dist-info/top_level.txt
click_odoo_contrib-1.23.1.dist-info/RECORD
