Metadata-Version: 2.4
Name: click-odoo-contrib
Version: 1.23.1
Summary: click-odoo scripts collection
Home-page: http://github.com/acsone/click-odoo-contrib
Author: ACSONE SA/NV
Author-email: info@acsone.eu
License: LGPLv3+
Classifier: Development Status :: 4 - Beta
Classifier: Intended Audience :: Developers
Classifier: License :: OSI Approved :: GNU Lesser General Public License v3 or later (LGPLv3+)
Classifier: Programming Language :: Python :: 3.6
Classifier: Programming Language :: Python :: 3.7
Classifier: Programming Language :: Python :: 3.8
Classifier: Programming Language :: Python :: 3.9
Classifier: Programming Language :: Python :: 3.10
Classifier: Programming Language :: Python :: 3.11
Classifier: Framework :: Odoo
Requires-Python: >=3.6
License-File: LICENSE
Requires-Dist: click-odoo>=1.3.0
Requires-Dist: manifestoo-core>=0.7
Requires-Dist: importlib_resources; python_version < "3.9"
Dynamic: author
Dynamic: author-email
Dynamic: classifier
Dynamic: description
Dynamic: home-page
Dynamic: license
Dynamic: license-file
Dynamic: requires-dist
Dynamic: requires-python
Dynamic: summary
